CHANGELOG.md
LICENSE
growlery/__init__.py
growlery/__main__.py
growlery/cogs/__init__.py
growlery/cogs/hiscores.py
growlery/config.py
growlery/http_request.py
growlery/main.py
growlery/table.py
growlery-0.3.1.dist-info/LICENSE
growlery-0.3.1.dist-info/METADATA
growlery-0.3.1.dist-info/WHEEL
growlery-0.3.1.dist-info/RECORD
