Metadata-Version: 2.1
Name: growlery
Version: 0.3.1
Summary: An OSRS Discord bot for Clan Quest.
Home-page: https://pypi.org/project/clan-quest-osrs-discord-bot/
License: MIT
Keywords: python3,discord,runescape,osrs,oldschool
Author: Lari Liuhamo
Author-email: lari.liuhamo+pypi@gmail.com
Maintainer: Lari Liuhamo
Maintainer-email: lari.liuhamo+pypi@gmail.com
Requires-Python: >=3.10,<4.0
Classifier: Development Status :: 4 - Beta
Classifier: Environment :: Console
Classifier: Intended Audience :: End Users/Desktop
Classifier: Intended Audience :: Information Technology
Classifier: Intended Audience :: System Administrators
Classifier: License :: OSI Approved :: MIT License
Classifier: Natural Language :: English
Classifier: Operating System :: MacOS
Classifier: Operating System :: Microsoft :: Windows :: Windows 10
Classifier: Operating System :: Microsoft :: Windows :: Windows 11
Classifier: Operating System :: POSIX :: Linux
Classifier: Programming Language :: Python :: 3
Classifier: Programming Language :: Python :: 3.10
Classifier: Programming Language :: Python :: 3.11
Classifier: Programming Language :: Python :: 3.12
Classifier: Programming Language :: Python :: Implementation :: CPython
Classifier: Programming Language :: Python :: Implementation :: PyPy
Classifier: Topic :: Communications :: Chat
Classifier: Topic :: Games/Entertainment
Classifier: Topic :: Utilities
Classifier: Typing :: Typed
Requires-Dist: aiohttp (>=3.9.1,<4.0.0)
Requires-Dist: discord.py (>=2.3.2,<3.0.0)
Requires-Dist: python-dotenv (>=1.0.0,<2.0.0)
Requires-Dist: reactionmenu (>=3.1.3,<4.0.0)
Project-URL: Changelog, https://github.com/Diapolo10/clan-quest-osrs-discord-bot/blob/main/CHANGELOG.md
Project-URL: Documentation, https://github.com/Diapolo10/clan-quest-osrs-discord-bot/tree/main/docs
Project-URL: Repository, https://github.com/Diapolo10/clan-quest-osrs-discord-bot
Project-URL: Tracker, https://github.com/Diapolo10/clan-quest-osrs-discord-bot/issues
